{
  "mappings": {
    "content": {
      "_source": {
        "enabled": {{ source_enabled | default(true) | tojson }}
      },
      "dynamic": "strict",
      "_all": {
        "enabled": false
      },
      "properties": {
        "body": {
          "type": "text",
          "analyzer": "english"
        }
      }
    },
    "percolator": {
      "dynamic": "strict",
      "_all": {
        "enabled": false
      },
      "properties": {
        "query": {
          "type": "percolator"
        }
      }
    }
  }
}